blockgamebot/__init__.py
blockgamebot/api.py
blockgamebot-1.4.dist-info/LICENSE
blockgamebot-1.4.dist-info/METADATA
blockgamebot-1.4.dist-info/WHEEL
blockgamebot-1.4.dist-info/top_level.txt
blockgamebot-1.4.dist-info/RECORD
