Metadata-Version: 2.1
Name: blockgamebot
Version: 1.4
Summary: An API Wrapper for the block game bot api
Author: asov
Author-email: asov <noemtdev@gmail.com>
Project-URL: Homepage, https://github.com/noemtdev/api-wrapper
Project-URL: Bug Tracker, https://github.com/noemtdev/api-wrapper/issues
Keywords: python,hypixel,skyblock,scammerlist,blockgamebot,blockgamebot
Classifier: Programming Language :: Python :: 3
Classifier: License :: OSI Approved :: MIT License
Classifier: Operating System :: OS Independent
Requires-Python: >=3.7
License-File: LICENSE
Requires-Dist: aiohttp
